relational_tool/__init__.py
relational_tool/maintenance.py
relational_tool/optimizations.py
relational_tool/optimizer.py
relational_tool/parser.py
relational_tool/querysplit.py
relational_tool/relation.py
relational_tool/relational.py
relational_tool/rtypes.py
Relational_tool-0.0.1.dist-info/LICENSE
Relational_tool-0.0.1.dist-info/METADATA
Relational_tool-0.0.1.dist-info/WHEEL
Relational_tool-0.0.1.dist-info/top_level.txt
Relational_tool-0.0.1.dist-info/RECORD
